{
	"info": {
		"_postman_id": "bae0bfe7-906a-4d15-967b-a27fdec5787d",
		"name": "User Management API",
		"description": "API endpoints for user management system",
		"schema": "https://schema.getpostman.com/json/collection/v2.1.0/collection.json",
		"_exporter_id": "7706013"
	},
	"item": [
		{
			"name": "Register",
			"request": {
				"method": "POST",
				"header": [
					{
						"key": "Content-Type",
						"value": "application/json"
					}
				],
				"body": {
					"mode": "raw",
					"raw": ""
				},
				"url": {
					"raw": "{{base_url}}/register",
					"host": [
						"{{base_url}}"
					],
					"path": [
						"register"
					]
				}
			},
			"response": []
		},
		{
			"name": "Login",
			"event": [
				{
					"listen": "test",
					"script": {
						"exec": [
							"var res = pm.response.json()",
							"if(res.token) {",
							"    pm.collectionVariables.set(\"token\", res.token);",
							"}"
						],
						"type": "text/javascript",
						"packages": {}
					}
				}
			],
			"request": {
				"method": "POST",
				"header": [
					{
						"key": "Content-Type",
						"value": "application/json"
					}
				],
				"body": {
					"mode": "raw",
					"raw": "{\n    \"email\": \"malai.suk@example.com\",\n    \"password\": \"password123\"\n}"
				},
				"url": {
					"raw": "{{base_url}}/login",
					"host": [
						"{{base_url}}"
					],
					"path": [
						"login"
					]
				}
			},
			"response": []
		},
		{
			"name": "Get Profile",
			"request": {
				"method": "GET",
				"header": [
					{
						"key": "Authorization",
						"value": "Bearer {{token}}"
					}
				],
				"url": {
					"raw": "{{base_url}}/profile/:id",
					"host": [
						"{{base_url}}"
					],
					"path": [
						"profile",
						":id"
					],
					"variable": [
						{
							"key": "id",
							"value": "1"
						}
					]
				}
			},
			"response": []
		},
		{
			"name": "Update Profile",
			"request": {
				"method": "POST",
				"header": [
					{
						"key": "Authorization",
						"value": "Bearer {{token}}"
					},
					{
						"key": "Content-Type",
						"value": "application/json"
					}
				],
				"body": {
					"mode": "raw",
					"raw": ""
				},
				"url": {
					"raw": "{{base_url}}/profile",
					"host": [
						"{{base_url}}"
					],
					"path": [
						"profile"
					]
				}
			},
			"response": []
		},
		{
			"name": "Delete Profile",
			"request": {
				"method": "DELETE",
				"header": [
					{
						"key": "Authorization",
						"value": "Bearer {{token}}"
					},
					{
						"key": "Content-Type",
						"value": "application/json"
					}
				],
				"body": {
					"mode": "raw",
					"raw": ""
				},
				"url": {
					"raw": "{{base_url}}/profile",
					"host": [
						"{{base_url}}"
					],
					"path": [
						"profile"
					]
				}
			},
			"response": []
		},
		{
			"name": "Change Password",
			"request": {
				"method": "POST",
				"header": [
					{
						"key": "Authorization",
						"value": "Bearer {{token}}"
					},
					{
						"key": "Content-Type",
						"value": "application/json"
					}
				],
				"body": {
					"mode": "raw",
					"raw": "{\n    \"password\": \"password123\",\n    \"newPassword\": \"password1234567\",\n    \"confirmNewPassword\": \"password1234567\"\n}"
				},
				"url": {
					"raw": "{{base_url}}/change-password",
					"host": [
						"{{base_url}}"
					],
					"path": [
						"change-password"
					]
				}
			},
			"response": []
		}
	],
	"variable": [
		{
			"key": "base_url",
			"value": "http://localhost:3000",
			"type": "string"
		},
		{
			"key": "token",
			"value": "faketokenuser_1",
			"type": "string"
		}
	]
}